pytrip98gui-1.7.0.dist-info/licenses/AUTHORS.rst
pytripgui/__init__.py
pytripgui/_version.py
pytripgui/main.py
pytripgui/messages.py
pytripgui/util.py
pytripgui/add_vois_vc/__init__.py
pytripgui/add_vois_vc/add_vois_cont.py
pytripgui/add_vois_vc/add_vois_view.py
pytripgui/add_vois_vc/voi_widget.py
pytripgui/add_vois_vc/add_single_voi_vc/__init__.py
pytripgui/add_vois_vc/add_single_voi_vc/add_single_voi_cont.py
pytripgui/add_vois_vc/add_single_voi_vc/add_single_voi_view.py
pytripgui/add_vois_vc/widgets/__init__.py
pytripgui/app_logic/__init__.py
pytripgui/app_logic/app_callbacks.py
pytripgui/app_logic/charts.py
pytripgui/app_logic/gui_executor.py
pytripgui/app_logic/patient_tree.py
pytripgui/app_logic/viewcanvas.py
pytripgui/canvas_vc/__init__.py
pytripgui/canvas_vc/canvas_controller.py
pytripgui/canvas_vc/canvas_view.py
pytripgui/canvas_vc/gui_state.py
pytripgui/canvas_vc/plot_model.py
pytripgui/canvas_vc/projection_selector.py
pytripgui/canvas_vc/objects/__init__.py
pytripgui/canvas_vc/objects/ctx.py
pytripgui/canvas_vc/objects/data_base.py
pytripgui/canvas_vc/objects/dos.py
pytripgui/canvas_vc/objects/let.py
pytripgui/canvas_vc/objects/vc_text.py
pytripgui/canvas_vc/objects/vdx.py
pytripgui/canvas_vc/plotter/__init__.py
pytripgui/canvas_vc/plotter/coordinate_info.py
pytripgui/canvas_vc/plotter/mpl_plotter.py
pytripgui/canvas_vc/plotter/bars/__init__.py
pytripgui/canvas_vc/plotter/bars/bar_base.py
pytripgui/canvas_vc/plotter/bars/ctx_bar.py
pytripgui/canvas_vc/plotter/bars/dos_bar.py
pytripgui/canvas_vc/plotter/bars/let_bar.py
pytripgui/canvas_vc/plotter/bars/projection_enum.py
pytripgui/canvas_vc/plotter/images/__init__.py
pytripgui/canvas_vc/plotter/images/ctx_image.py
pytripgui/canvas_vc/plotter/images/dose_image.py
pytripgui/canvas_vc/plotter/images/let_image.py
pytripgui/canvas_vc/plotter/images/patient_image_base.py
pytripgui/canvas_vc/plotter/managers/__init__.py
pytripgui/canvas_vc/plotter/managers/blit_manager.py
pytripgui/canvas_vc/plotter/managers/placement_manager.py
pytrip98gui-1.7.0.dist-info/METADATA
pytrip98gui-1.7.0.dist-info/WHEEL
pytrip98gui-1.7.0.dist-info/entry_points.txt
pytrip98gui-1.7.0.dist-info/top_level.txt
pytrip98gui-1.7.0.dist-info/RECORD
